classifier_free_guidance_pytorch/__init__.py
classifier_free_guidance_pytorch/attend.py
classifier_free_guidance_pytorch/bge.py
classifier_free_guidance_pytorch/classifier_free_guidance_pytorch.py
classifier_free_guidance_pytorch/open_clip.py
classifier_free_guidance_pytorch/t5.py
classifier_free_guidance_pytorch/tokenizer.py
classifier_free_guidance_pytorch/typing.py
classifier_free_guidance_pytorch/data/bpe_simple_vocab_16e6.txt
classifier_free_guidance_pytorch-0.7.1.dist-info/LICENSE
classifier_free_guidance_pytorch-0.7.1.dist-info/METADATA
classifier_free_guidance_pytorch-0.7.1.dist-info/WHEEL
classifier_free_guidance_pytorch-0.7.1.dist-info/top_level.txt
classifier_free_guidance_pytorch-0.7.1.dist-info/RECORD
